swarmauri_standard/README.md
swarmauri_standard/__init__.py
swarmauri_standard/agents/QAAgent.py
swarmauri_standard/agents/RagAgent.py
swarmauri_standard/agents/SimpleConversationAgent.py
swarmauri_standard/agents/ToolAgent.py
swarmauri_standard/agents/__init__.py
swarmauri_standard/chains/CallableChain.py
swarmauri_standard/chains/ChainStep.py
swarmauri_standard/chains/ContextChain.py
swarmauri_standard/chains/PromptContextChain.py
swarmauri_standard/chains/__init__.py
swarmauri_standard/chunkers/DelimiterBasedChunker.py
swarmauri_standard/chunkers/FixedLengthChunker.py
swarmauri_standard/chunkers/MdSnippetChunker.py
swarmauri_standard/chunkers/SentenceChunker.py
swarmauri_standard/chunkers/SlidingWindowChunker.py
swarmauri_standard/chunkers/__init__.py
swarmauri_standard/control_panels/ControlPanel.py
swarmauri_standard/control_panels/__init__.py
swarmauri_standard/conversations/Conversation.py
swarmauri_standard/conversations/MaxSizeConversation.py
swarmauri_standard/conversations/MaxSystemContextConversation.py
swarmauri_standard/conversations/SessionCacheConversation.py
swarmauri_standard/conversations/__init__.py
swarmauri_standard/dataconnectors/GoogleDriveDataConnector.py
swarmauri_standard/dataconnectors/__init__.py
swarmauri_standard/decorators/__init__.py
swarmauri_standard/decorators/deprecate.py
swarmauri_standard/decorators/maybe_async.py
swarmauri_standard/decorators/retry_on_status_codes.py
swarmauri_standard/decorators/tool_decorator.py
swarmauri_standard/distances/CanberraDistance.py
swarmauri_standard/distances/ChebyshevDistance.py
swarmauri_standard/distances/ChiSquaredDistance.py
swarmauri_standard/distances/CosineDistance.py
swarmauri_standard/distances/EuclideanDistance.py
swarmauri_standard/distances/HaversineDistance.py
swarmauri_standard/distances/JaccardIndexDistance.py
swarmauri_standard/distances/LevenshteinDistance.py
swarmauri_standard/distances/ManhattanDistance.py
swarmauri_standard/distances/SorensenDiceDistance.py
swarmauri_standard-0.7.5.dist-info/LICENSE
swarmauri_standard-0.7.5.dist-info/METADATA
swarmauri_standard-0.7.5.dist-info/WHEEL
swarmauri_standard-0.7.5.dist-info/RECORD
