Metadata-Version: 2.3
Name: swarmauri-standard
Version: 0.7.5
Summary: This repository includes standard components within the Swarmauri framework.
License: Apache-2.0
Author: Jacob Stewart
Author-email: jacob@swarmauri.com
Requires-Python: >=3.10,<3.13
Classifier: License :: OSI Approved :: Apache Software License
Classifier: Programming Language :: Python :: 3.10
Classifier: Programming Language :: Python :: 3.11
Classifier: Programming Language :: Python :: 3.12
Requires-Dist: aiofiles
Requires-Dist: httpx (>=0.27.0)
Requires-Dist: joblib (>=1.4.0)
Requires-Dist: numpy
Requires-Dist: pandas
Requires-Dist: pillow (>=11.1.0)
Requires-Dist: pydantic (>=2.9.2)
Requires-Dist: rich
Requires-Dist: swarmauri_base
Requires-Dist: swarmauri_core
Requires-Dist: toml (>=0.10.2)
Requires-Dist: typing_extensions
